.gitignore
LICENSE
README.rst
setup.py
tox.ini
okonomi/__init__.py
okonomi/middleware.py
okonomi/models.py
okonomi/urls.py
okonomi/utils.py
okonomi/views.py
okonomi.egg-info/PKG-INFO
okonomi.egg-info/SOURCES.txt
okonomi.egg-info/dependency_links.txt
okonomi.egg-info/not-zip-safe
okonomi.egg-info/top_level.txt
okonomi/templatetags/__init__.py
okonomi/templatetags/okonomi.py
okonomi/tests/__init__.py
okonomi/tests/helpers.py
okonomi/tests/settings.py
okonomi/tests/test_middleware.py
okonomi/tests/templatetags/test_okonomi.py