Metadata-Version: 1.0
Name: okonomi
Version: 0.1.1
Summary: smart JS loading for Django
Home-page: https://github.com/coxmediagroup/okonomi
Author: Cox Media Group
Author-email: opensource@coxinc.com
License: MIT
Keywords: javascript,loader,templatetag,django
Platform: UNKNOWN
Classifier: Development Status :: 4 - Beta
Classifier: Intended Audience :: Developers
Classifier: License :: OSI Approved :: MIT License
Classifier: Topic :: Software Development :: Build Tools
Classifier: Topic :: Software Development :: Libraries
Classifier: Topic :: Software Development :: Testing
Classifier: Topic :: Utilities
Classifier: Operating System :: MacOS :: MacOS X
Classifier: Operating System :: Microsoft :: Windows
Classifier: Operating System :: POSIX
Classifier: Programming Language :: Python :: 2.5
Classifier: Programming Language :: Python :: 2.6
Classifier: Programming Language :: Python :: 2.7
